LICENSE.txt
MANIFEST.in
README.md
README.rst
setup.cfg
setup.py
onlinepayments/__init__.py
onlinepayments/sdk/__init__.py
onlinepayments/sdk/api_exception.py
onlinepayments/sdk/api_resource.py
onlinepayments/sdk/authenticator.py
onlinepayments/sdk/authorization_exception.py
onlinepayments/sdk/call_context.py
onlinepayments/sdk/client.py
onlinepayments/sdk/communication_exception.py
onlinepayments/sdk/communicator.py
onlinepayments/sdk/communicator_configuration.py
onlinepayments/sdk/connection.py
onlinepayments/sdk/data_object.py
onlinepayments/sdk/declined_payment_exception.py
onlinepayments/sdk/declined_payout_exception.py
onlinepayments/sdk/declined_refund_exception.py
onlinepayments/sdk/declined_transaction_exception.py
onlinepayments/sdk/endpoint_configuration.py
onlinepayments/sdk/factory.py
onlinepayments/sdk/i_client.py
onlinepayments/sdk/idempotence_exception.py
onlinepayments/sdk/marshaller.py
onlinepayments/sdk/marshaller_syntax_exception.py
onlinepayments/sdk/meta_data_provider.py
onlinepayments/sdk/multipart_form_data_object.py
onlinepayments/sdk/multipart_form_data_request.py
onlinepayments/sdk/not_found_exception.py
onlinepayments/sdk/param_request.py
onlinepayments/sdk/payment_platform_exception.py
onlinepayments/sdk/pooled_connection.py
onlinepayments/sdk/proxy_configuration.py
onlinepayments/sdk/reference_exception.py
onlinepayments/sdk/request_header.py
onlinepayments/sdk/request_param.py
onlinepayments/sdk/response_exception.py
onlinepayments/sdk/response_header.py
onlinepayments/sdk/uploadable_file.py
onlinepayments/sdk/validation_exception.py
onlinepayments/sdk/defaultimpl/__init__.py
onlinepayments/sdk/defaultimpl/authorization_type.py
onlinepayments/sdk/defaultimpl/default_authenticator.py
onlinepayments/sdk/defaultimpl/default_connection.py
onlinepayments/sdk/defaultimpl/default_marshaller.py
onlinepayments/sdk/domain/__init__.py
onlinepayments/sdk/domain/account_on_file.py
onlinepayments/sdk/domain/account_on_file_attribute.py
onlinepayments_sdk_python2.egg-info/PKG-INFO
onlinepayments_sdk_python2.egg-info/SOURCES.txt
onlinepayments_sdk_python2.egg-info/dependency_links.txt
onlinepayments_sdk_python2.egg-info/requires.txt
onlinepayments_sdk_python2.egg-info/top_level.txt