Metadata-Version: 1.1
Name: onlinepayments-sdk-python2
Version: 4.23.0
Summary: SDK to communicate with the Online Payments platform using the Online Payments Server API
Home-page: https://github.com/wl-online-payments-direct/sdk-python2
Author: Worldline Direct support team
Author-email: 82139942+worldline-direct-support-team@users.noreply.github.com
License: MIT
Keywords: Online Payments SDK
Platform: python 2.7
Classifier: Development Status :: 5 - Production/Stable
Classifier: Operating System :: POSIX :: Linux
Classifier: Operating System :: Microsoft :: Windows
Classifier: Intended Audience :: Developers
Classifier: Programming Language :: Python :: 2 :: Only
Classifier: Programming Language :: Python :: 2.7
Classifier: Topic :: Office/Business :: Financial
Classifier: License :: OSI Approved :: MIT License
